flowserv/__init__.py
flowserv/config.py
flowserv/error.py
flowserv/scanner.py
flowserv/version.py
flowserv/client/__init__.py
flowserv/client/api.py
flowserv/client/app/__init__.py
flowserv/client/app/base.py
flowserv/client/app/data.py
flowserv/client/app/run.py
flowserv/client/app/workflow.py
flowserv/client/cli/__init__.py
flowserv/client/cli/admin.py
flowserv/client/cli/app.py
flowserv/client/cli/base.py
flowserv/client/cli/cleanup.py
flowserv/client/cli/group.py
flowserv/client/cli/gui.py
flowserv/client/cli/parameter.py
flowserv/client/cli/repository.py
flowserv/client/cli/run.py
flowserv/client/cli/table.py
flowserv/client/cli/uploads.py
flowserv/client/cli/user.py
flowserv/client/cli/workflow.py
flowserv/client/gui/__init__.py
flowserv/client/gui/app.py
flowserv/client/gui/forms.py
flowserv/client/gui/widget.py
flowserv/controller/__init__.py
flowserv/controller/base.py
flowserv/controller/remote/__init__.py
flowserv/controller/remote/client.py
flowserv/controller/remote/engine.py
flowserv/controller/remote/monitor.py
flowserv/controller/serial/__init__.py
flowserv/controller/serial/engine/__init__.py
flowserv/controller/serial/engine/base.py
flowserv/controller/serial/engine/config.json
flowserv/controller/serial/engine/config.py
flowserv/controller/serial/engine/runner.py
flowserv/controller/serial/engine/validate.py
flowserv/controller/serial/workflow/__init__.py
flowserv/controller/serial/workflow/base.py
flowserv/controller/serial/workflow/parser.py
flowserv/controller/serial/workflow/result.py
flowserv/controller/worker/__init__.py
flowserv/controller/worker/base.py
flowserv/controller/worker/code.py
flowserv/controller/worker/config.py
flowserv/controller/worker/docker.py
flowserv/controller/worker/manager.py
flowserv/controller/worker/notebook.py
flowserv/controller/worker/subprocess.py
flowserv/model/__init__.py
flowserv/model/auth.py
flowserv/model/base.py
flowserv/model/constraint.py
flowserv/model/database.py
flowserv/model/files.py
flowserv_core-0.9.4.dist-info/LICENSE
flowserv_core-0.9.4.dist-info/METADATA
flowserv_core-0.9.4.dist-info/WHEEL
flowserv_core-0.9.4.dist-info/entry_points.txt
flowserv_core-0.9.4.dist-info/top_level.txt
flowserv_core-0.9.4.dist-info/RECORD
