Metadata-Version: 2.1
Name: flowserv-core
Version: 0.9.4
Summary: Reproducible and Reusable Data Analysis Workflow Server (Core Infrastructure)
Home-page: https://github.com/scailfin/flowserv-core
Author: Heiko Mueller
Author-email: heiko.muller@gmail.com
License: MIT
Keywords: reproducibility workflows benchmarks data-analysis
Platform: UNKNOWN
Classifier: License :: OSI Approved :: MIT License
Classifier: Operating System :: OS Independent
Classifier: Programming Language :: Python :: 3
Classifier: Programming Language :: Python :: 3.7
Classifier: Programming Language :: Python :: 3.8
Classifier: Programming Language :: Python :: 3.9
Classifier: Programming Language :: Python
License-File: LICENSE
Requires-Dist: future
Requires-Dist: appdirs (>=1.4.4)
Requires-Dist: gitpython
Requires-Dist: paramiko
Requires-Dist: passlib
Requires-Dist: python-dateutil
Requires-Dist: jsonschema
Requires-Dist: pyyaml (>=5.1)
Requires-Dist: requests
Requires-Dist: SQLAlchemy (>=1.3.18)
Requires-Dist: Click
Requires-Dist: pyyaml-include
Provides-Extra: aws
Requires-Dist: boto3 ; extra == 'aws'
Provides-Extra: dev
Requires-Dist: flake8 ; extra == 'dev'
Requires-Dist: python-language-server ; extra == 'dev'
Requires-Dist: boto3 ; extra == 'dev'
Requires-Dist: docker ; extra == 'dev'
Requires-Dist: google-cloud-storage ; extra == 'dev'
Requires-Dist: jupyter ; extra == 'dev'
Requires-Dist: papermill ; extra == 'dev'
Requires-Dist: coverage (>=5.0) ; extra == 'dev'
Requires-Dist: pytest ; extra == 'dev'
Requires-Dist: pytest-cov ; extra == 'dev'
Provides-Extra: docker
Requires-Dist: docker ; extra == 'docker'
Provides-Extra: docs
Requires-Dist: Sphinx ; extra == 'docs'
Requires-Dist: sphinx-rtd-theme ; extra == 'docs'
Requires-Dist: sphinxcontrib-apidoc ; extra == 'docs'
Provides-Extra: full
Requires-Dist: boto3 ; extra == 'full'
Requires-Dist: docker ; extra == 'full'
Requires-Dist: google-cloud-storage ; extra == 'full'
Requires-Dist: jupyter ; extra == 'full'
Requires-Dist: papermill ; extra == 'full'
Requires-Dist: psycopg2-binary ; extra == 'full'
Requires-Dist: streamlit ; extra == 'full'
Provides-Extra: gc
Requires-Dist: google-cloud-storage ; extra == 'gc'
Provides-Extra: gui
Requires-Dist: streamlit ; extra == 'gui'
Provides-Extra: notebooks
Requires-Dist: jupyter ; extra == 'notebooks'
Requires-Dist: papermill ; extra == 'notebooks'
Provides-Extra: postgres
Requires-Dist: psycopg2-binary ; extra == 'postgres'
Provides-Extra: tests
Requires-Dist: coverage (>=5.0) ; extra == 'tests'
Requires-Dist: pytest ; extra == 'tests'
Requires-Dist: pytest-cov ; extra == 'tests'
